btype/__init__.py
btype/btype.py
btype-0.1.7.dist-info/licenses/LICENSE
btype-0.1.7.dist-info/METADATA
btype-0.1.7.dist-info/WHEEL
btype-0.1.7.dist-info/top_level.txt
btype-0.1.7.dist-info/RECORD
