Metadata-Version: 2.4
Name: btype
Version: 0.1.7
Summary: Package for dealing with binary structures
Home-page: https://github.com/tgree/btype
Author: Terry Greeniaus
Author-email: terrygreeniaus@gmail.com
License: LGPLv2
Keywords: struct type binary
Classifier: Operating System :: OS Independent
Classifier: Programming Language :: Python :: 3
Classifier: License :: OSI Approved :: GNU Lesser General Public License v2 (LGPLv2)
Requires-Python: >=3.0
License-File: LICENSE
Dynamic: license-file
